{
  "keywordGroups": [
    {
      "groupName": "매일경제",
      "keywords": [
        "매일경제"
      ]
    },
    {
      "groupName": "비트코인",
      "keywords": [
        "비트코인"
      ]
    },
    {
      "groupName": "한국경제",
      "keywords": [
        "한국경제"
      ]
    },
    {
      "groupName": "xrp",
      "keywords": [
        "xrp"
      ]
    },
    {
      "groupName": "조선일보",
      "keywords": [
        "조선일보"
      ]
    },
    {
      "groupName": "이더리움",
      "keywords": [
        "이더리움"
      ]
    },
    {
      "groupName": "블록미디어",
      "keywords": [
        "블록미디어"
      ]
    },
    {
      "groupName": "네이트",
      "keywords": [
        "네이트"
      ]
    }
  ],
  "topTerms": [
    [
      "매일경제",
      41
    ],
    [
      "비트코인",
      33
    ],
    [
      "한국경제",
      30
    ],
    [
      "xrp",
      27
    ],
    [
      "조선일보",
      25
    ],
    [
      "이더리움",
      25
    ],
    [
      "블록미디어",
      25
    ],
    [
      "네이트",
      24
    ],
    [
      "트럼프",
      23
    ],
    [
      "리플",
      21
    ],
    [
      "뉴시스",
      19
    ],
    [
      "지디넷코리아",
      19
    ],
    [
      "연합뉴스",
      17
    ],
    [
      "글로벌이코노믹",
      17
    ],
    [
      "파월",
      16
    ],
    [
      "돌파",
      16
    ],
    [
      "정답",
      16
    ],
    [
      "디지털투데이",
      15
    ],
    [
      "ai",
      14
    ],
    [
      "삼성",
      14
    ],
    [
      "biz",
      13
    ],
    [
      "etf",
      13
    ],
    [
      "만에",
      13
    ],
    [
      "kr",
      13
    ],
    [
      "콘텐츠",
      12
    ],
    [
      "chosun",
      12
    ],
    [
      "chosun biz",
      12
    ],
    [
      "경향신문",
      12
    ],
    [
      "암호화폐",
      12
    ],
    [
      "원전",
      12
    ],
    [
      "외국인",
      12
    ],
    [
      "8월",
      12
    ],
    [
      "엔비디아",
      12
    ],
    [
      "동아일보",
      11
    ],
    [
      "google",
      10
    ],
    [
      "뉴스에서",
      10
    ],
    [
      "전체",
      10
    ],
    [
      "보기",
      10
    ],
    [
      "google 뉴스에서",
      10
    ],
    [
      "뉴스에서 전체",
      10
    ],
    [
      "전체 콘텐츠",
      10
    ],
    [
      "콘텐츠 보기",
      10
    ],
    [
      "마켓인",
      10
    ],
    [
      "이유",
      10
    ],
    [
      "한겨레",
      10
    ],
    [
      "삼성전자",
      9
    ],
    [
      "9월",
      9
    ],
    [
      "미국",
      9
    ],
    [
      "리플 xrp",
      9
    ],
    [
      "완공",
      9
    ],
    [
      "bntnews",
      9
    ],
    [
      "co",
      9
    ],
    [
      "정답 8월",
      9
    ],
    [
      "bntnews co",
      9
    ],
    [
      "co kr",
      9
    ],
    [
      "로봇",
      9
    ],
    [
      "금리인하",
      8
    ],
    [
      "상승",
      8
    ],
    [
      "두산에너빌리티",
      8
    ],
    [
      "msn",
      8
    ],
    [
      "정부",
      8
    ],
    [
      "최고가",
      8
    ],
    [
      "중단",
      8
    ],
    [
      "시장",
      8
    ],
    [
      "ceo",
      8
    ],
    [
      "해외",
      8
    ],
    [
      "달러",
      8
    ],
    [
      "코인리더스",
      8
    ],
    [
      "아재폰",
      7
    ],
    [
      "10",
      7
    ],
    [
      "케데헌",
      7
    ],
    [
      "랠리",
      7
    ],
    [
      "일제히",
      7
    ],
    [
      "아파트",
      7
    ],
    [
      "ai타임스",
      7
    ],
    [
      "전망",
      7
    ],
    [
      "서울",
      7
    ],
    [
      "해상",
      7
    ],
    [
      "앞둔",
      7
    ],
    [
      "규모",
      7
    ]
  ],
  "itemCount": 116
}
